CHANGES.rst
MANIFEST.in
README.rst
setup.py
collective/__init__.py
collective.address.egg-info/PKG-INFO
collective.address.egg-info/SOURCES.txt
collective.address.egg-info/dependency_links.txt
collective.address.egg-info/entry_points.txt
collective.address.egg-info/namespace_packages.txt
collective.address.egg-info/not-zip-safe
collective.address.egg-info/requires.txt
collective.address.egg-info/top_level.txt
collective/address/__init__.py
collective/address/behaviors.py
collective/address/configure.zcml
collective/address/vocabulary.py
collective/address/locales/collective.address.pot
collective/address/locales/update.sh
collective/address/locales/de/LC_MESSAGES/collective.address.po
collective/address/locales/fr/LC_MESSAGES/collective.address.po
collective/address/locales/it/LC_MESSAGES/collective.address.po
docs/INSTALL.txt
docs/LICENSE.GPL
docs/LICENSE.txt