Metadata-Version: 1.1
Name: collective.address
Version: 1.6
Summary: Dexterity address behavior.
Home-page: https://github.com/collective/collective.address
Author: Johannes Raggam
Author-email: raggam-nl@adm.at
License: GPL
Keywords: plone collective address
Platform: UNKNOWN
Classifier: Framework :: Plone
Classifier: Programming Language :: Python
